{
    "$schema": "https://schema.management.azure.com/schemas/2015-01-01/deploymentParameters.json#",
    "contentVersion": "1.0.0.0",
    "parameters": {
        "subscriptionId": {
            "value": "f323bb2b-a56b-4930-ac59-7e3216839c2d"
        },
        "name": {
            "value": "mocear"
        },
        "location": {
            "value": "Germany West Central"
        },
        "hostingPlanName": {
            "value": "alejandraservplan"
        },
        "serverFarmResourceGroup": {
            "value": "FinalTestAlejandra"
        },
        "alwaysOn": {
            "value": true
        },
        "linuxFxVersion": {
            "value": "PYTHON|3.7"
        },
        "repoUrl": {
            "value": "https://github.com/kakashidota/armdeploy"
        },
        "branch": {
            "value": "main"
        }
    }
}